golemcpp_waflib-1.0.3.dist-info/licenses/waf/LICENSE
waflib/Build.py
waflib/ConfigSet.py
waflib/Configure.py
waflib/Context.py
waflib/Errors.py
waflib/Logs.py
waflib/Node.py
waflib/Options.py
waflib/Runner.py
waflib/Scripting.py
waflib/Task.py
waflib/TaskGen.py
waflib/Utils.py
waflib/__init__.py
waflib/ansiterm.py
waflib/fixpy2.py
waflib/processor.py
waflib/Tools/__init__.py
waflib/Tools/ar.py
waflib/Tools/asm.py
waflib/Tools/bison.py
waflib/Tools/c.py
waflib/Tools/c_aliases.py
waflib/Tools/c_config.py
waflib/Tools/c_osx.py
waflib/Tools/c_preproc.py
waflib/Tools/c_tests.py
waflib/Tools/ccroot.py
waflib/Tools/clang.py
waflib/Tools/clangxx.py
waflib/Tools/compiler_c.py
waflib/Tools/compiler_cxx.py
waflib/Tools/compiler_d.py
waflib/Tools/compiler_fc.py
waflib/Tools/cs.py
waflib/Tools/cxx.py
waflib/Tools/d.py
waflib/Tools/d_config.py
waflib/Tools/d_scan.py
waflib/Tools/dbus.py
waflib/Tools/dmd.py
waflib/Tools/errcheck.py
waflib/Tools/fc.py
waflib/Tools/fc_config.py
waflib/Tools/fc_scan.py
waflib/Tools/flex.py
waflib/Tools/g95.py
waflib/Tools/gas.py
waflib/Tools/gcc.py
waflib/Tools/gdc.py
waflib/Tools/gfortran.py
waflib/Tools/glib2.py
waflib/Tools/gnu_dirs.py
waflib/Tools/gxx.py
waflib/Tools/icc.py
waflib/Tools/icpc.py
waflib/Tools/ifort.py
waflib/Tools/intltool.py
waflib/Tools/irixcc.py
waflib/Tools/javaw.py
waflib/Tools/ldc2.py
waflib/Tools/lua.py
waflib/Tools/md5_tstamp.py
waflib/Tools/msvc.py
waflib/Tools/nasm.py
waflib/Tools/nobuild.py
waflib/Tools/perl.py
waflib/Tools/python.py
waflib/Tools/qt5.py
waflib/Tools/ruby.py
waflib/Tools/suncc.py
waflib/Tools/suncxx.py
waflib/Tools/tex.py
waflib/Tools/vala.py
waflib/Tools/waf_unit_test.py
waflib/Tools/wafcache.py
waflib/Tools/winres.py
waflib/Tools/xlc.py
waflib/Tools/xlcxx.py
waflib/extras/__init__.py
waflib/extras/batched_cc.py
waflib/extras/biber.py
waflib/extras/bjam.py
waflib/extras/blender.py
waflib/extras/boost.py
waflib/extras/build_file_timestamp.py
waflib/extras/build_logs.py
waflib/extras/buildcopy.py
waflib/extras/c_bgxlc.py
waflib/extras/c_dumbpreproc.py
golemcpp_waflib-1.0.3.dist-info/METADATA
golemcpp_waflib-1.0.3.dist-info/WHEEL
golemcpp_waflib-1.0.3.dist-info/top_level.txt
golemcpp_waflib-1.0.3.dist-info/RECORD
