Metadata-Version: 2.4
Name: golemcpp-waflib
Version: 1.0.3
Summary: Modified waflib for Golem (original project https://gitlab.com/ita1024/waf)
Author-email: Barnabé BALP <contact@barnabebalp.fr>
License-Expression: BSD-3-Clause
Project-URL: Homepage, https://gitlab.com/bbalp/waf
Project-URL: Repository, https://gitlab.com/bbalp/waf.git
Project-URL: Issues, https://gitlab.com/bbalp/waf/-/issues
Keywords: cpp
Classifier: Programming Language :: Python :: 3
Classifier: Operating System :: OS Independent
Requires-Python: >=3.10
License-File: waf/LICENSE
Dynamic: license-file
